headersformat/__init__.py
headersformat/colors.py
headersformat/core.py
headersformat-0.1.0.dist-info/LICENSE
headersformat-0.1.0.dist-info/METADATA
headersformat-0.1.0.dist-info/WHEEL
headersformat-0.1.0.dist-info/top_level.txt
headersformat-0.1.0.dist-info/RECORD
