Metadata-Version: 2.1
Name: headersformat
Version: 0.1.0
Summary: 爬虫辅助工具-请求头headers一键格式化
Home-page: UNKNOWN
Author: jia666666
Author-email: 1732330472@qq.com
License: apache 3.0
Platform: UNKNOWN
Requires-Python: >=3.0
License-File: LICENSE
Requires-Dist: pyexecjs
Requires-Dist: selectolax
Requires-Dist: pyperclip
